notice/__init__.py
notice/lark.py
notice/notice.py
notice/sms.py
notice/version.py
notice/voice.py
notice_/__init__.py
notice_/lark.py
notice_/notice.py
notice_/sms.py
notice_/voice.py
notice_py-0.1.7.dist-info/LICENSE
notice_py-0.1.7.dist-info/METADATA
notice_py-0.1.7.dist-info/WHEEL
notice_py-0.1.7.dist-info/top_level.txt
notice_py-0.1.7.dist-info/RECORD
