Metadata-Version: 2.1
Name: notice-py
Version: 0.1.7
Summary: lark/sms/voice notice package
Home-page: https://github.com/zefzhou/notice_py
Author: zefzhou44
Author-email: zefzhou44@gmail.com
License: UNKNOWN
Platform: UNKNOWN
Classifier: Programming Language :: Python :: 3
Classifier: License :: OSI Approved :: MIT License
Classifier: Operating System :: OS Independent
Requires-Python: >=3.8.0
Requires-Dist: requests
Requires-Dist: alibabacloud-dysmsapi20170525
Requires-Dist: tenacity
Requires-Dist: python-dotenv
